aretomo_ctf_4_relion/__init__.py
aretomo_ctf_4_relion/_version.py
aretomo_ctf_4_relion/aretomo_ctf_4_relion.py
aretomo_ctf_4_relion/utils.py
AreTomo_CTF_for_RELION_5-0.1.dist-info/LICENSE
AreTomo_CTF_for_RELION_5-0.1.dist-info/METADATA
AreTomo_CTF_for_RELION_5-0.1.dist-info/WHEEL
AreTomo_CTF_for_RELION_5-0.1.dist-info/entry_points.txt
AreTomo_CTF_for_RELION_5-0.1.dist-info/top_level.txt
AreTomo_CTF_for_RELION_5-0.1.dist-info/RECORD
