Metadata-Version: 2.1
Name: AreTomo_CTF_for_RELION_5
Version: 0.1
Summary: AreTomo CTF estimation for RELION 5
Author: Euan Pyle
Author-email: euanpyle@gmail.com
License: BSD 3-Clause License
Project-URL: homepage, https://github.com/EuanPyle/AreTomo_CTF_for_RELION_5
Project-URL: repository, https://github.com/EuanPyle/AreTomo_CTF_for_RELION_5
Classifier: Development Status :: 3 - Alpha
Classifier: License :: OSI Approved :: BSD License
Classifier: Programming Language :: Python :: 3
Classifier: Programming Language :: Python :: 3.6
Classifier: Programming Language :: Python :: 3.7
Classifier: Programming Language :: Python :: 3.8
Classifier: Programming Language :: Python :: 3.9
Classifier: Programming Language :: Python :: 3.10
Requires-Python: >=3.6
License-File: LICENSE
Requires-Dist: numpy
Requires-Dist: pandas
Requires-Dist: starfile
Requires-Dist: typer
